qiskit_ibm_runtime_mcp_server/__init__.py
qiskit_ibm_runtime_mcp_server/ibm_runtime.py
qiskit_ibm_runtime_mcp_server/py.typed
qiskit_ibm_runtime_mcp_server/server.py
qiskit_ibm_runtime_mcp_server/utils.py
qiskit_ibm_runtime_mcp_server-0.3.0.dist-info/METADATA
qiskit_ibm_runtime_mcp_server-0.3.0.dist-info/WHEEL
qiskit_ibm_runtime_mcp_server-0.3.0.dist-info/entry_points.txt
qiskit_ibm_runtime_mcp_server-0.3.0.dist-info/licenses/LICENSE
qiskit_ibm_runtime_mcp_server-0.3.0.dist-info/RECORD
