Metadata-Version: 2.4
Name: qiskit-ibm-runtime-mcp-server
Version: 0.3.0
Summary: MCP server for IBM Quantum computing services through Qiskit IBM Runtime
Project-URL: Homepage, https://github.com/Qiskit/mcp-servers
Project-URL: Repository, https://github.com/Qiskit/mcp-servers
Project-URL: Documentation, https://github.com/Qiskit/mcp-servers/tree/main/qiskit-ibm-runtime-mcp-server#readme
Project-URL: Bug Tracker, https://github.com/Qiskit/mcp-servers/issues
Author-email: "Quantum+AI Team. IBM Quantum" <Quantum.Plus.AI@ibm.com>
License: Apache-2.0
License-File: LICENSE
Requires-Python: <3.15,>=3.10
Requires-Dist: fastmcp>=2.8.1
Requires-Dist: nest-asyncio>=1.5.0
Requires-Dist: pydantic>=2.0.0
Requires-Dist: python-dotenv>=1.0.0
Requires-Dist: qiskit-ibm-runtime>=0.40.0
Requires-Dist: qiskit-mcp-server
Provides-Extra: all
Requires-Dist: bandit[toml]>=1.7.0; extra == 'all'
Requires-Dist: mypy>=1.15.0; extra == 'all'
Requires-Dist: pre-commit>=3.5.0; extra == 'all'
Requires-Dist: pytest-asyncio>=0.21.0; extra == 'all'
Requires-Dist: pytest-cov>=4.1.0; extra == 'all'
Requires-Dist: pytest-mock>=3.11.0; extra == 'all'
Requires-Dist: pytest>=7.4.0; extra == 'all'
Requires-Dist: ruff>=0.11.13; extra == 'all'
Provides-Extra: dev
Requires-Dist: bandit[toml]>=1.7.0; extra == 'dev'
Requires-Dist: mypy>=1.15.0; extra == 'dev'
Requires-Dist: pre-commit>=3.5.0; extra == 'dev'
Requires-Dist: ruff>=0.11.13; extra == 'dev'
Provides-Extra: examples
Requires-Dist: langchain-mcp-adapters>=0.1.0; extra == 'examples'
Requires-Dist: langchain>=1.2.0; extra == 'examples'
Requires-Dist: python-dotenv>=1.0.0; extra == 'examples'
Provides-Extra: test
Requires-Dist: pytest-asyncio>=0.21.0; extra == 'test'
Requires-Dist: pytest-cov>=4.1.0; extra == 'test'
Requires-Dist: pytest-mock>=3.11.0; extra == 'test'
Requires-Dist: pytest>=7.4.0; extra == 'test'
